{
	"info": {
		"_postman_id": "319dff22-b0ba-4709-a329-0479f298dd6e",
		"name": "Gama Sports",
		"schema": "https://schema.getpostman.com/json/collection/v2.1.0/collection.json"
	},
	"item": [
		{
			"name": "User",
			"item": [
				{
					"name": "Create User",
					"request": {
						"method": "POST",
						"header": [],
						"body": {
							"mode": "raw",
							"raw": "{\r\n    \"name\": \"Maria da Silva\",\r\n    \"cpf\": \"450.911.660-84\",\r\n    \"birthdate\": \"10/05/1997\",\r\n    \"gender\": \"F\",\r\n    \"phone\": \"11928492749\",\r\n    \"email\": \"maria.silva@gmail.com\",\r\n    \"password\": \"12345678\"\r\n}",
							"options": {
								"raw": {
									"language": "json"
								}
							}
						},
						"url": {
							"raw": "http://localhost:5000/users",
							"protocol": "http",
							"host": [
								"localhost"
							],
							"port": "5000",
							"path": [
								"users"
							]
						}
					},
					"response": []
				},
				{
					"name": "Forgot password",
					"request": {
						"method": "POST",
						"header": [],
						"body": {
							"mode": "raw",
							"raw": "{\r\n    \"email\": \"lucas.almeida3423@gmail.com\"\r\n}",
							"options": {
								"raw": {
									"language": "json"
								}
							}
						},
						"url": {
							"raw": "http://localhost:5000/forgot-password",
							"protocol": "http",
							"host": [
								"localhost"
							],
							"port": "5000",
							"path": [
								"forgot-password"
							]
						}
					},
					"response": []
				},
				{
					"name": "Reset Password",
					"request": {
						"method": "POST",
						"header": [],
						"body": {
							"mode": "raw",
							"raw": "{\r\n    \"newpassword\": \"1234567890\"\r\n}",
							"options": {
								"raw": {
									"language": "json"
								}
							}
						},
						"url": {
							"raw": "http://localhost:5000/reset-password/b2b123ilP3C2iyWqHRQcvuQxA8eUaIlfWscwGP9lRk5VxlKx9jEt4mZeC",
							"protocol": "http",
							"host": [
								"localhost"
							],
							"port": "5000",
							"path": [
								"reset-password",
								"b2b123ilP3C2iyWqHRQcvuQxA8eUaIlfWscwGP9lRk5VxlKx9jEt4mZeC"
							]
						}
					},
					"response": []
				},
				{
					"name": "Get User",
					"request": {
						"method": "GET",
						"header": [],
						"url": {
							"raw": ""
						}
					},
					"response": []
				}
			],
			"protocolProfileBehavior": {}
		},
		{
			"name": "Login",
			"request": {
				"auth": {
					"type": "basic",
					"basic": [
						{
							"key": "password",
							"value": "12345678",
							"type": "string"
						},
						{
							"key": "username",
							"value": "pedro.alcantara@gmail.com",
							"type": "string"
						}
					]
				},
				"method": "POST",
				"header": [],
				"body": {
					"mode": "raw",
					"raw": "{\r\n    \"login\": \"maria.silva@gmail.com\",\r\n    \"password\": \"12345678\"\r\n}",
					"options": {
						"raw": {
							"language": "json"
						}
					}
				},
				"url": {
					"raw": "http://localhost:5000/login",
					"protocol": "http",
					"host": [
						"localhost"
					],
					"port": "5000",
					"path": [
						"login"
					]
				}
			},
			"response": []
		},
		{
			"name": "List Products",
			"request": {
				"method": "GET",
				"header": [],
				"url": {
					"raw": ""
				}
			},
			"response": []
		},
		{
			"name": "Save Cart",
			"request": {
				"method": "POST",
				"header": [],
				"url": {
					"raw": ""
				}
			},
			"response": []
		}
	],
	"protocolProfileBehavior": {}
}